simple_frame/__init__.py
simple_frame/__main__.py
simple_frame-0.0.0.dist-info/LICENSE.txt
simple_frame-0.0.0.dist-info/METADATA
simple_frame-0.0.0.dist-info/WHEEL
simple_frame-0.0.0.dist-info/top_level.txt
simple_frame-0.0.0.dist-info/RECORD
