Metadata-Version: 2.1
Name: simple-frame
Version: 0.0.0
Summary: Simpler version of dataframes
Author-email: Johannes <johannes-horler@posteo.org>
License: The MIT License (MIT)
Classifier: License :: OSI Approved :: MIT License
Classifier: Programming Language :: Python
Classifier: Programming Language :: Python :: 3
Requires-Python: >=3.11
License-File: LICENSE.txt
